sparse_transform/__init__.py
sparse_transform/qsft/__init__.py
sparse_transform/qsft/qsft.py
sparse_transform/qsft/codes/BCH.py
sparse_transform/qsft/codes/__init__.py
sparse_transform/qsft/signals/__init__.py
sparse_transform/qsft/signals/input_signal.py
sparse_transform/qsft/signals/input_signal_subsampled.py
sparse_transform/qsft/signals/synthetic_signal.py
sparse_transform/qsft/utils/__init__.py
sparse_transform/qsft/utils/general.py
sparse_transform/qsft/utils/query.py
sparse_transform/qsft/utils/reconstruct.py
sparse_transform-0.2.1.dist-info/METADATA
sparse_transform-0.2.1.dist-info/WHEEL
sparse_transform-0.2.1.dist-info/licenses/LICENSE
sparse_transform-0.2.1.dist-info/RECORD
